MANIFEST.in
setup.py
mark2.egg-info/PKG-INFO
mark2.egg-info/SOURCES.txt
mark2.egg-info/dependency_links.txt
mark2.egg-info/entry_points.txt
mark2.egg-info/requires.txt
mark2.egg-info/top_level.txt
mark2.egg-info/zip-safe
mk2/__init__.py
mk2/launcher.py
mk2/manager.py
mk2/properties.py
mk2/shared.py
mk2/user_client.py
mk2/events/__init__.py
mk2/events/console.py
mk2/events/error.py
mk2/events/hook.py
mk2/events/player.py
mk2/events/server.py
mk2/events/stat.py
mk2/events/user.py
mk2/plugins/__init__.py
mk2/plugins/alert.py
mk2/plugins/backup.py
mk2/plugins/irc.py
mk2/plugins/log.py
mk2/plugins/mcbouncer.py
mk2/plugins/monitor.py
mk2/plugins/mumble.py
mk2/plugins/push.py
mk2/plugins/redis.py
mk2/plugins/rss.py
mk2/plugins/save.py
mk2/plugins/script.py
mk2/plugins/shutdown.py
mk2/plugins/su.py
mk2/plugins/trigger.py
mk2/resources/mark2.default.properties
mk2/resources/mark2rc.default.properties
mk2/resources/server.default.properties
mk2/servers/__init__.py
mk2/servers/bukkit.py
mk2/servers/feed_the_beast.py
mk2/servers/forge.py
mk2/servers/libigot.py
mk2/servers/mcpcplus.py
mk2/servers/nukkit.py
mk2/servers/spigot.py
mk2/servers/technic.py
mk2/servers/vanilla.py
mk2/services/__init__.py
mk2/services/builtin.py
mk2/services/console_tracking.py
mk2/services/ping.py
mk2/services/process.py
mk2/services/user_server.py
mk2/test/__init__.py
mk2/test/test_events.py
mk2/test/test_plugins.py
mk2/test/test_process.py