Metadata-Version: 1.1
Name: mark2
Version: 0.1.4.1
Summary: Minecraft server wrapper
Home-page: http://mark2.io/
Author: Barnaby Gale & Ed Kellett
Author-email: not.real.email@mark2.io
License: MIT
Keywords: mark2 minecraft server wrapper
Platform: UNKNOWN
Classifier: Development Status :: 3 - Alpha
Classifier: Environment :: Console
Classifier: Framework :: Twisted
Classifier: Intended Audience :: System Administrators
Classifier: License :: OSI Approved :: MIT License
Classifier: Natural Language :: English
Classifier: Operating System :: POSIX
Classifier: Operating System :: POSIX :: Linux
Classifier: Programming Language :: Python :: 2 :: Only
Classifier: Topic :: Utilities
